odoo/addons/project_task_report/README.rst
odoo/addons/project_task_report/__init__.py
odoo/addons/project_task_report/__manifest__.py
odoo/addons/project_task_report/i18n/es.po
odoo/addons/project_task_report/i18n/fr.po
odoo/addons/project_task_report/i18n/project_task_report.pot
odoo/addons/project_task_report/i18n/sl.po
odoo/addons/project_task_report/static/description/icon.png
odoo/addons/project_task_report/views/project_task_chatter_report.xml
odoo/addons/project_task_report/views/project_task_report.xml
odoo11_addon_project_task_report-11.0.1.0.0.99.dev8.dist-info/METADATA
odoo11_addon_project_task_report-11.0.1.0.0.99.dev8.dist-info/WHEEL
odoo11_addon_project_task_report-11.0.1.0.0.99.dev8.dist-info/top_level.txt
odoo11_addon_project_task_report-11.0.1.0.0.99.dev8.dist-info/RECORD
